qtoml/__init__.py
qtoml/__main__.py
qtoml/decoder.py
qtoml/encoder.py
qtoml/py.typed
qtoml-0.3.1.dist-info/entry_points.txt
qtoml-0.3.1.dist-info/LICENSE
qtoml-0.3.1.dist-info/WHEEL
qtoml-0.3.1.dist-info/METADATA
qtoml-0.3.1.dist-info/RECORD
