Metadata-Version: 2.1
Name: qtoml
Version: 0.3.1
Summary: New TOML encoder/decoder
Home-page: https://github.com/alethiophile/qtoml
License: MIT
Author: alethiophile
Author-email: tomdicksonhunt@gmail.com
Requires-Python: >=3.6,<4.0
Classifier: License :: OSI Approved :: MIT License
Classifier: Operating System :: OS Independent
Classifier: Programming Language :: Python :: 3
Classifier: Programming Language :: Python :: 3.6
Classifier: Programming Language :: Python :: 3.7
Classifier: Programming Language :: Python :: 3.8
Classifier: Programming Language :: Python :: 3.9
Classifier: Topic :: Software Development :: Libraries :: Python Modules
Requires-Dist: attrs (>=19.3.0,<22.0)
Requires-Dist: click (>=7.0,<9.0)
Project-URL: Repository, https://github.com/alethiophile/qtoml
